psycopg2_client/client.py
psycopg2_client/settings.py
psycopg2_client/query_by_key/query.py
psycopg2_client/query_by_key/query_util.py
psycopg2_client/query_by_key/settings.py
psycopg2_client-1.0.7.dist-info/licenses/LICENSE
psycopg2_client-1.0.7.dist-info/METADATA
psycopg2_client-1.0.7.dist-info/WHEEL
psycopg2_client-1.0.7.dist-info/top_level.txt
psycopg2_client-1.0.7.dist-info/RECORD
