Metadata-Version: 2.4
Name: psycopg2-client
Version: 1.0.7
Summary: Psycopg2 helper function to run PostgreSQL query with #if support
Author-email: Gu Park <doctorgu@kakao.com>
License: MIT
Project-URL: homepage, https://github.com/doctorgu/psycopg2-client
Project-URL: repository, https://github.com/doctorgu/psycopg2-client
Project-URL: documentation, https://github.com/doctorgu/psycopg2-client
Keywords: psycopg2 client,psycopg2 helper
Requires-Python: >=3.11
License-File: LICENSE
Requires-Dist: psycopg2-binary
Requires-Dist: pyhumps
Requires-Dist: typing-extensions
Requires-Dist: python-dotenv
Requires-Dist: pydantic-settings
Requires-Dist: Flask
Provides-Extra: test
Requires-Dist: pytest; extra == "test"
Requires-Dist: pytest-cov; extra == "test"
Requires-Dist: pytest-env; extra == "test"
Requires-Dist: pytest-mock; extra == "test"
Requires-Dist: pytest-asyncio; extra == "test"
Dynamic: license-file
